pemo/__init__.py
pemo/_version.py
pemo/builder.py
pemo/commonoss.py
pemo/configutil.py
pemo/main.py
pemo/requirements.txt
pemo/tencent.py
pemo/ziputil.py
pemo/resources/config.json
pemo-0.1.1.dist-info/METADATA
pemo-0.1.1.dist-info/WHEEL
pemo-0.1.1.dist-info/entry_points.txt
pemo-0.1.1.dist-info/top_level.txt
pemo-0.1.1.dist-info/RECORD
