Metadata-Version: 2.1
Name: pemo
Version: 0.1.1
Summary: 一个帮助用户下载服务器上的文件的命令行工具, 它依托于云存储服务实现中转
Author-email: kenny <ztxemail@163.com>
Classifier: Programming Language :: Python :: 3
Classifier: License :: OSI Approved :: MIT License
Classifier: Operating System :: OS Independent
Requires-Python: >=3.0
Requires-Dist: click ==8.1.6
Requires-Dist: cos-python-sdk-v5 ==1.9.25
Requires-Dist: zipfile
